TAPE/__init__.py
TAPE/deconvolution.py
TAPE/model.py
TAPE/simulation.py
TAPE/train.py
TAPE/utils.py
scTAPE-1.1.2.dist-info/LICENSE
scTAPE-1.1.2.dist-info/METADATA
scTAPE-1.1.2.dist-info/WHEEL
scTAPE-1.1.2.dist-info/top_level.txt
scTAPE-1.1.2.dist-info/RECORD
