Metadata-Version: 2.1
Name: scTAPE
Version: 1.1.2
Summary: deep learning tools for bulk RNA-seq deconvolution and gene expression analysis
Home-page: https://github.com/poseidonchan/TAPE
Author: Yanshuo Chen
Author-email: poseidonchan@icloud.com
License: GPL-3.0 License
Platform: any
Requires-Python: >=3.7
License-File: LICENSE
Requires-Dist: torch (>=1.8.0)
Requires-Dist: numpy (>=1.21)
Requires-Dist: pandas (>=1.0)
Requires-Dist: matplotlib (>=3.4)
Requires-Dist: anndata (>=0.7.6)
Requires-Dist: tqdm (>=4.6)
Requires-Dist: scikit-learn (>=0.23)
Requires-Dist: seaborn (>=0.11)
